examples/__init__.py
examples/custom_settings.py
examples/flask_api_service/__init__.py
examples/flask_api_service/app.py
examples/flask_api_service/custom_settings.py
examples/flask_api_service/fake_db.py
flexi_settings/__init__.py
flexi_settings/base_settings.py
flexi_settings/context.py
flexi_settings/docker_resolver.py
flexi_settings/env_resolver.py
flexi_settings/override_visitor.py
flexi_settings/resolver.py
flexi_settings/tree_data.py
flexi_settings/tree_data_resolver.py
flexi_settings/tree_resolver_visitor.py
flexi_settings/var_resolver.py
flexi_settings/variable.py
flexi_settings/version.py
flexi_settings/visitors.py
flexi_settings-1.0.1.dev270739073.dist-info/LICENSE
flexi_settings-1.0.1.dev270739073.dist-info/METADATA
flexi_settings-1.0.1.dev270739073.dist-info/WHEEL
flexi_settings-1.0.1.dev270739073.dist-info/top_level.txt
flexi_settings-1.0.1.dev270739073.dist-info/RECORD
