Metadata-Version: 2.1
Name: flexi-settings
Version: 1.0.1.dev270739073
Summary: Manages embedded variables and blending settings
Home-page: https://gitlab.com/bredbeddle-open/flexi-settings
Author: Curtis Forrester
Author-email: crforresterspam@pm.me
License: MIT
Platform: UNKNOWN
Classifier: Development Status :: 5 - Production/Stable
Classifier: Environment :: Console
Classifier: Framework :: Flake8
Classifier: Intended Audience :: Developers
Classifier: License :: OSI Approved :: MIT License
Classifier: Programming Language :: Python
Classifier: Programming Language :: Python :: 3.7
Requires-Python: >=3.7
Requires-Dist: pkg-version-mgr
Requires-Dist: decorators
Requires-Dist: PyYAML
Requires-Dist: jmespath
